claude_command/__init__.py
claude_command/__main__.py
claude_command/server.py
claude_command/settings.py
claude_command/streaming.py
claude_command/clients/__init__.py
claude_command/clients/anthropic.py
claude_command/clients/factory.py
claude_command/clients/gemini.py
claude_command/clients/interface.py
claude_command/clients/openai.py
claude_command/dialog/__init__.py
claude_command/dialog/missions.py
claude_command/dialog/single.py
claude_command/missions/__init__.py
claude_command/missions/brainstorm.py
claude_command/missions/query.py
claude_command/missions/recon.py
claude_command/missions/review.py
claude_command/storage/__init__.py
claude_command/storage/manager.py
claude_command/storage/naming.py
claude_command/utils/__init__.py
claude_command/utils/text.py
claude_command-0.6.0.dist-info/METADATA
claude_command-0.6.0.dist-info/WHEEL
claude_command-0.6.0.dist-info/entry_points.txt
claude_command-0.6.0.dist-info/licenses/LICENSE
claude_command-0.6.0.dist-info/RECORD
