Metadata-Version: 2.4
Name: claude-command
Version: 0.6.0
Summary: Claude Command - AI command center for Claude Code
Project-URL: Homepage, https://github.com/shaneholloman/mcp-claude-command
Project-URL: Repository, https://github.com/shaneholloman/mcp-claude-command
Project-URL: Issues, https://github.com/shaneholloman/mcp-claude-command/issues
Author: Shane Holloman
License: MIT
License-File: LICENSE
Classifier: Development Status :: 5 - Production/Stable
Classifier: Intended Audience :: Developers
Classifier: License :: OSI Approved :: MIT License
Classifier: Programming Language :: Python :: 3
Classifier: Programming Language :: Python :: 3.10
Classifier: Programming Language :: Python :: 3.11
Classifier: Programming Language :: Python :: 3.12
Classifier: Topic :: Software Development :: Libraries :: Python Modules
Requires-Python: >=3.10
Requires-Dist: anthropic
Requires-Dist: fastmcp
Requires-Dist: google-generativeai
Requires-Dist: openai
Provides-Extra: dev
Requires-Dist: mypy; extra == 'dev'
Requires-Dist: ruff; extra == 'dev'
